api/__init__.py
api/admin.py
api/aiohttp.py
api/apps.py
api/business.py
api/migrations/__init__.py
api/models.py
api/views.py
poet_api-3.0.4.dist-info/METADATA
poet_api-3.0.4.dist-info/WHEEL
poet_api-3.0.4.dist-info/licenses/LICENSE
poet_api-3.0.4.dist-info/RECORD
