Metadata-Version: 2.4
Name: poet-api
Version: 3.0.4
Summary: Requests for all
License: BSD-3-Clause
License-File: LICENSE
Author: raratiru
Requires-Python: >=3.11,<4.0
Classifier: License :: OSI Approved :: BSD License
Classifier: Programming Language :: Python :: 3
Classifier: Programming Language :: Python :: 3.11
Classifier: Programming Language :: Python :: 3.12
Classifier: Programming Language :: Python :: 3.13
Classifier: Programming Language :: Python :: 3.14
Requires-Dist: aiohttp (>=3.11.13,<4.0.0)
Requires-Dist: filelock (>=3.12.3,<4.0.0)
Requires-Dist: pyrate-limiter (>=3,<4)
